MANIFEST.in
README.md
setup.py
SeqPresenceAbsence/FASconCAT-G_v1.04.pl
SeqPresenceAbsence/SeqPresenceAbsence.py
SeqPresenceAbsence/__init__.py
seqPresenceAbsence.egg-info/PKG-INFO
seqPresenceAbsence.egg-info/SOURCES.txt
seqPresenceAbsence.egg-info/dependency_links.txt
seqPresenceAbsence.egg-info/entry_points.txt
seqPresenceAbsence.egg-info/requires.txt
seqPresenceAbsence.egg-info/top_level.txt