Metadata-Version: 2.1
Name: seqPresenceAbsence
Version: 0.2.2
Summary: Package for checking for the presence/absence of markers against a set of samples
Home-page: https://github.com/bfssi-forest-dussault/SeqPresenceAbsence
Author: Forest Dussault
Author-email: forest.dussault@canada.ca
License: UNKNOWN
Platform: UNKNOWN
Requires-Python: ~=3.6
